tnm/circuit/__init__.py
tnm/circuit/_breaker.py
tnm/circuit/_helpers.py
tnm/circuit/_path.py
tnm/circuit/_typeguard.py
tnm/circuit/_utils.py
tnm/circuit/exceptions.py
tnm/circuit/interfaces.py
tnm/circuit/policies.py
tnm/circuit/_backends/__init__.py
tnm/circuit/_backends/redis_backend.py
tnm/circuit/_backends/sqlite_backend.py
tnm/circuit/_redis/__init__.py
tnm/circuit/storage/lua/circuit_failure_record.lua
tnm/circuit/storage/lua/circuit_get_count.lua
tnm/circuit/storage/lua/circuit_reset.lua
tnm_circuit_breaker-0.2.2.dist-info/licenses/LICENSE
tnm_circuit_breaker-0.2.2.dist-info/METADATA
tnm_circuit_breaker-0.2.2.dist-info/WHEEL
tnm_circuit_breaker-0.2.2.dist-info/top_level.txt
tnm_circuit_breaker-0.2.2.dist-info/RECORD
