Metadata-Version: 2.4
Name: tnm-circuit-breaker
Version: 0.2.2
Summary: A ligthweight circuit breaker implementation for Python.
Author-email: Justice Sandram <justicesandram@gmail.com>
Project-URL: Repository, https://github.com/mpamba/tnm-circuit-breaker
Keywords: breaker,circuit,circuit breaker,redis
Classifier: Programming Language :: Python :: 3
Classifier: Programming Language :: Python :: 3.11
Classifier: Programming Language :: Python :: 3.12
Classifier: Programming Language :: Python :: 3.13
Classifier: Topic :: Internet :: WWW/HTTP
Classifier: Topic :: Software Development :: Libraries :: Python Modules
Requires-Python: >=3.11
License-File: LICENSE
Requires-Dist: typeguard>=4.0.1
Requires-Dist: inflect>=7.4.0
Provides-Extra: redis
Requires-Dist: redis[hiredis]>=5.3.1; extra == "redis"
Provides-Extra: dev
Requires-Dist: pytest>=7; extra == "dev"
Requires-Dist: pytest_asyncio; extra == "dev"
Requires-Dist: pytest-cov; extra == "dev"
Requires-Dist: tox; extra == "dev"
Requires-Dist: ruff; extra == "dev"
Requires-Dist: black>=23; extra == "dev"
Requires-Dist: mypy>=1.9; extra == "dev"
Requires-Dist: twine; extra == "dev"
Requires-Dist: build; extra == "dev"
Requires-Dist: pydantic; extra == "dev"
Requires-Dist: httpx; extra == "dev"
Dynamic: license-file
